infoweb/__init__.py
infoweb/infoweb.py
check_web-1.0.0.dist-info/METADATA
check_web-1.0.0.dist-info/WHEEL
check_web-1.0.0.dist-info/top_level.txt
check_web-1.0.0.dist-info/RECORD
